turbo/__init__.py
turbo/apps.py
turbo/classes.py
turbo/components.py
turbo/consumers.py
turbo/metaclass.py
turbo/module_loading.py
turbo/registry.py
turbo/shortcuts.py
turbo/signals.py
turbo/static/turbo/js/reconnecting-websocket.min.js
turbo/static/turbo/js/turbo-django.js
turbo/static/turbo/js/turbo.min.js
turbo/templates/turbo/components/broadcast_component.html
turbo/templates/turbo/head.html
turbo/templates/turbo/stream.html
turbo/templates/turbo/turbo_stream_source.html
turbo/templatetags/__init__.py
turbo/templatetags/turbo_streams.py
django_turbojs-0.5.3.dist-info/LICENSE
django_turbojs-0.5.3.dist-info/METADATA
django_turbojs-0.5.3.dist-info/WHEEL
django_turbojs-0.5.3.dist-info/RECORD
