Metadata-Version: 2.1
Name: django-turbojs
Version: 0.5.3
Summary: Integrate Hotwire Turbo with Django allowing for a Python-driven dynamic web experience.
License: MIT
Author: Nikita Marchant
Author-email: C4ptainCrunch@github-username.x
Requires-Python: >=3.8,<4.0
Classifier: Environment :: Web Environment
Classifier: Framework :: Django
Classifier: Framework :: Django :: 3.2
Classifier: Intended Audience :: Developers
Classifier: License :: OSI Approved :: MIT License
Classifier: Operating System :: OS Independent
Classifier: Programming Language :: Python
Classifier: Programming Language :: Python :: 3
Classifier: Programming Language :: Python :: 3.8
Classifier: Programming Language :: Python :: 3.9
Classifier: Programming Language :: Python :: 3.10
Classifier: Programming Language :: Python :: 3.11
Classifier: Programming Language :: Python :: 3.12
Classifier: Programming Language :: Python :: 3 :: Only
Classifier: Programming Language :: Python :: 3.7
Requires-Dist: Django (>=3.2.0)
Requires-Dist: channels (>=2.0.0)
